pytest_pointers/__init__.py
pytest_pointers/plugin.py
pytest_pointers/tests/__init__.py
pytest_pointers/tests/mock_structure/__init__.py
pytest_pointers/tests/mock_structure/for_func_finder.py
pytest_pointers/tests/test_plugin.py
pytest_pointers/tests/test_utils.py
pytest_pointers/utils.py
pytest_pointers-0.3.1.dist-info/entry_points.txt
pytest_pointers-0.3.1.dist-info/WHEEL
pytest_pointers-0.3.1.dist-info/METADATA
pytest_pointers-0.3.1.dist-info/RECORD
