Metadata-Version: 2.1
Name: pytest-pointers
Version: 0.3.1
Summary: Pytest plugin to define functions you test with special marks for better navigation and reports
Home-page: https://github.com/jaklimoff/pytest-pointers
Keywords: plugin,pytest
Author: Jack Klimov
Author-email: jaklimoff@gmail.com
Requires-Python: >=3.7,<4.0
Classifier: Programming Language :: Python :: 3
Classifier: Programming Language :: Python :: 3.7
Classifier: Programming Language :: Python :: 3.8
Classifier: Programming Language :: Python :: 3.9
Requires-Dist: libcst (>=0.3.15,<0.4.0)
Requires-Dist: rich
Project-URL: Repository, https://github.com/jaklimoff/pytest-pointers
